{
  "collapse-filter": false,
  "search": "",
  "showTags": true,
  "showAttachments": false,
  "hideUnresolved": false,
  "showOrphans": true,
  "collapse-color-groups": true,
  "colorGroups": [],
  "collapse-display": false,
  "showArrow": false,
  "textFadeMultiplier": 0.6,
  "nodeSizeMultiplier": 1.35025773195876,
  "lineSizeMultiplier": 2.4110824742268,
  "collapse-forces": false,
  "centerStrength": 0.518713248970312,
  "repelStrength": 10,
  "linkStrength": 1,
  "linkDistance": 198,
  "scale": 0.5087618855792584,
  "close": true
}